lyrebird/__init__.py
lyrebird/application.py
lyrebird/background.py
lyrebird/base_server.py
lyrebird/config.py
lyrebird/event.py
lyrebird/manager.py
lyrebird/task.py
lyrebird/version.py
lyrebird/client/__init__.py
lyrebird/mock/__init__.py
lyrebird/mock/cache.py
lyrebird/mock/console_helper.py
lyrebird/mock/context.py
lyrebird/mock/event_bus.py
lyrebird/mock/filesystem.py
lyrebird/mock/logger_config.py
lyrebird/mock/logger_helper.py
lyrebird/mock/mock_server.py
lyrebird/mock/plugin_manager.py
lyrebird/mock/blueprints/__init__.py
lyrebird/mock/blueprints/api.py
lyrebird/mock/blueprints/api_mock.py
lyrebird/mock/blueprints/ui.py
lyrebird/mock/data_manager/__init__.py
lyrebird/mock/data_manager/data.py
lyrebird/mock/data_manager/data_group.py
lyrebird/mock/data_manager/data_repo.py
lyrebird/mock/data_manager/exceptions.py
lyrebird/mock/data_manager/serialize.py
lyrebird/mock/handlers/__init__.py
lyrebird/mock/handlers/cache_handler.py
lyrebird/mock/handlers/handler_context.py
lyrebird/mock/handlers/mock_handler.py
lyrebird/mock/handlers/path_not_found_handler.py
lyrebird/mock/handlers/proxy_handler.py
lyrebird/mock/reporter/__init__.py
lyrebird/mock/reporter/report_handler.py
lyrebird/mock/static/css/AdminLTE.css
lyrebird/mock/static/css/AdminLTE.min.css
lyrebird/mock/static/css/dataTables.bootstrap.min.css
lyrebird/mock/static/css/alt/AdminLTE-bootstrap-social.css
lyrebird/mock/static/css/alt/AdminLTE-bootstrap-social.min.css
lyrebird/mock/static/css/alt/AdminLTE-fullcalendar.css
lyrebird/mock/static/css/alt/AdminLTE-fullcalendar.min.css
lyrebird/mock/static/css/alt/AdminLTE-select2.css
lyrebird/mock/static/css/alt/AdminLTE-select2.min.css
lyrebird/mock/static/css/alt/AdminLTE-without-plugins.css
lyrebird/mock/static/css/alt/AdminLTE-without-plugins.min.css
lyrebird/mock/static/css/skins/_all-skins.css
lyrebird/mock/static/css/skins/_all-skins.min.css
lyrebird/mock/static/css/skins/skin-black-light.css
lyrebird-0.12.1.dist-info/METADATA
lyrebird-0.12.1.dist-info/RECORD
lyrebird-0.12.1.dist-info/WHEEL
lyrebird-0.12.1.dist-info/entry_points.txt
lyrebird-0.12.1.dist-info/top_level.txt
