Metadata-Version: 2.1
Name: lyrebird
Version: 0.12.1
Summary: UNKNOWN
Home-page: https://github.com/meituan/lyrebird
Author: HBQA
License: UNKNOWN
Platform: UNKNOWN
Classifier: Programming Language :: Python :: 3 :: Only
Classifier: Programming Language :: Python :: 3.6
Classifier: License :: OSI Approved :: MIT License
Classifier: Operating System :: MacOS
Requires-Dist: flask
Requires-Dist: mitmproxy (==4.0.4)
Requires-Dist: requests
Requires-Dist: fire
Requires-Dist: colorama
Requires-Dist: genson
Requires-Dist: flask-socketio
Requires-Dist: flask-restful
Requires-Dist: beautifulsoup4
Requires-Dist: pycryptodome (==3.4.11)
Requires-Dist: portpicker
Requires-Dist: colorama
Requires-Dist: packaging
